<?xml version="1.0" encoding="UTF-8"?>
<Defs>
	<AlienRace.RaceSettings>
		<defName>orassanRaceSettings</defName>
		<pawnKindSettings>
			<startingColonists>
				<li>
					<pawnKindEntries>
						<li>
							<kindDefs>
								<li>OrassanVillager</li>
							</kindDefs>
							<chance>10.0</chance>
						</li>
						<li>
							<kindDefs>
								<li>HybridVillager</li>
							</kindDefs>
							<chance>10.0</chance>
						</li>
						<li>
							<kindDefs>
								<li>HumanVillager</li>
							</kindDefs>
							<chance>10.0</chance>
						</li>
					</pawnKindEntries>
					<factionDefs>
						<li>OrassanPlayerColony</li>
					</factionDefs>
				</li>
				<li>
					<pawnKindEntries>
						<li>
							<kindDefs>
								<li>Orassan</li>
							</kindDefs>
							<chance>10.0</chance>
						</li>
						<li>
							<kindDefs>
								<li>HybridVillager</li>
							</kindDefs>
							<chance>10.0</chance>
						</li>
					</pawnKindEntries>
					<factionDefs>
						<li>PlayerColony</li>
					</factionDefs>
				</li>
			</startingColonists>
			<alienslavekinds>
				<li>
					<kindDefs>
						<li>OrassanSlave</li>
					</kindDefs>
					<chance>5.0</chance>
				</li>
				<li>
					<kindDefs>
						<li>HybridVillager</li>
						</kindDefs>
					<chance>10.0</chance>
				</li>
			</alienslavekinds>
			<alienrefugeekinds>
				<li>
					<kindDefs>
						<li>OrassanRefugee</li>
					</kindDefs>
					<chance>15.0</chance>
				</li>
				<li>
					<kindDefs>
						<li>HybridVillager</li>
					</kindDefs>
					<chance>10.0</chance>
				</li>
			</alienrefugeekinds>
			<alienwandererkinds>
				<li>
					<pawnKindEntries>
						<li>
							<kindDefs>
								<li>OrassanTownGuard</li>
								<li>OrassanSniper</li>
								<li>OrassanGunner</li>
								<li>OrassanVillager</li>
								<li>HybridVillager</li>
							</kindDefs>
							<chance>15.0</chance>
						</li>
					</pawnKindEntries>
					<factionDefs>
						<li>PlayerColony</li>
					</factionDefs>
				</li>
			</alienwandererkinds>
		</pawnKindSettings>
		<!--<factionRelations>
                <li>
                    <factions>
                       <li>OrassanPlayerColony</li>
                    </factions>
                    <goodwill>
                       <min>100</min>
                       <max>100</max>
                    </goodwill>
                </li>               
            </factionRelations>-->
	</AlienRace.RaceSettings>
</Defs>